textPlay/Gsearch.py
textPlay/Modules Used.py
textPlay/__init__.py
textPlay/backend.py
textPlay/box.py
textPlay/cli.py
textPlay/colors.py
textPlay/encrypt_animation.py
textPlay/files.py
textPlay/loader.py
textPlay/logmsg.py
textPlay/main.py
textPlay/meta.py
textPlay/morse.py
textPlay/options.py
textPlay/password_generator.py
textPlay/progress_bar.py
textPlay/scraper.py
textPlay-1.1.5.dist-info/LICENSE
textPlay-1.1.5.dist-info/METADATA
textPlay-1.1.5.dist-info/WHEEL
textPlay-1.1.5.dist-info/entry_points.txt
textPlay-1.1.5.dist-info/top_level.txt
textPlay-1.1.5.dist-info/RECORD
