Metadata-Version: 2.1
Name: textPlay
Version: 1.1.5
Summary: A package for many unique text tools, to make your text beautiful.
Home-page: https://github.com/rakeshkanna-rk/textPlay
Author: Rakesh Kanna S
Author-email: rakeshkanna0108@gmail.com
License: Apache License 2.0
Project-URL: GitHub, https://github.com/rakeshkanna-rk/textPlay
Project-URL: Python Package Index, https://pypi.org/project/textPlay/
Keywords: text tools,cli,terminal,google search,web search,morse code,decode,encode,box,colors,options,password generator,progress bar,encryption animation,files,backend,source code
Classifier: Programming Language :: Python :: 3
Classifier: License :: OSI Approved :: Apache Software License
Classifier: Operating System :: OS Independent
Requires-Python: >=3.6
License-File: LICENSE
Requires-Dist: beautifulsoup4>=4.12.3
Requires-Dist: requests>=2.31.0
Requires-Dist: keyboard>=0.13.5
